.gitmodules
.travis.yml
LICENSE
README.rst
codemeta-harvest.json
setup.py
.github/workflows/foliatools.yml
FoLiA_tools.egg-info/PKG-INFO
FoLiA_tools.egg-info/SOURCES.txt
FoLiA_tools.egg-info/dependency_links.txt
FoLiA_tools.egg-info/entry_points.txt
FoLiA_tools.egg-info/requires.txt
FoLiA_tools.egg-info/top_level.txt
docs/Makefile
docs/source/conf.py
docs/source/index.rst
foliatools/__init__.py
foliatools/alpino2folia.py
foliatools/cgn2folia.py
foliatools/common.py
foliatools/conllu2folia.py
foliatools/dcoi2folia.py
foliatools/dcoi2folia.xsl
foliatools/folia2annotatedtxt.py
foliatools/folia2columns.py
foliatools/folia2dcoi.py
foliatools/folia2dcoi.xsl
foliatools/folia2html.py
foliatools/folia2html.xsl
foliatools/folia2rst.py
foliatools/folia2salt.py
foliatools/folia2stam.py
foliatools/folia2txt.py
foliatools/foliabench.py
foliatools/foliacat.py
foliatools/foliacorrect.py
foliatools/foliacount.py
foliatools/foliadiffeval.py
foliatools/foliaerase.py
foliatools/foliaeval.py
foliatools/foliafreqlist.py
foliatools/foliaid.py
foliatools/folialangid.py
foliatools/foliamerge.py
foliatools/foliaquery.py
foliatools/foliaquery1.py
foliatools/foliasetdefinition.py
foliatools/foliaspec.py
foliatools/foliaspec2json.py
foliatools/foliaspec2rdf.py
foliatools/foliasplit.py
foliatools/foliatextcontent.py
foliatools/foliatree.py
foliatools/foliaupgrade.py
foliatools/foliavalidator.py
foliatools/markdown2folia.py
foliatools/rst2folia.py
foliatools/tei2folia.py
foliatools/tei2folia.xsl
foliatools/transcribedspeech2folia.py
foliatools/txt2folia.py
foliatools/valkuilerrorcorpus2folia_input.xsl
foliatools/valkuilerrorcorpus2folia_ref.xsl
foliatools/vudnc2folia.xsl
foliatools/xslt.py
test/brainstorm
test/corpustest.sh
test/test.annotated.txt
test/test.columns.txt
test/test.fr.conllu
test/test.html
test/test.query1
test/test.query2
test/test.rst
test/test.sh
test/test.tei.xml
test/test.txt
test/test.xml
test/test2.txt