Metadata-Version: 2.4
Name: FoLiA-tools
Version: 2.5.9
Summary: FoLiA-tools contains various Python-based command line tools for working with FoLiA XML (Format for Linguistic Annotation)
Home-page: https://proycon.github.io/folia
Author: Maarten van Gompel
Author-email: proycon@anaproy.nl
License: GPL-3.0-only
Keywords: nlp,computational linguistics,search,folia,annotation
Classifier: Development Status :: 5 - Production/Stable
Classifier: Topic :: Text Processing :: Linguistic
Classifier: Programming Language :: Python :: 3.6
Classifier: Programming Language :: Python :: 3.7
Classifier: Programming Language :: Python :: 3.8
Classifier: Programming Language :: Python :: 3.9
Classifier: Programming Language :: Python :: 3.10
Classifier: Programming Language :: Python :: 3.11
Classifier: Operating System :: POSIX
Classifier: Intended Audience :: Developers
Classifier: Intended Audience :: Science/Research
Classifier: License :: OSI Approved :: GNU General Public License v3 (GPLv3)
License-File: LICENSE
Requires-Dist: folia>=2.5.9
Requires-Dist: lxml>=2.2
Requires-Dist: docutils
Requires-Dist: pyyaml
Requires-Dist: langid
Requires-Dist: conllu
Requires-Dist: requests
Requires-Dist: stam>=0.4.0
Dynamic: author
Dynamic: author-email
Dynamic: classifier
Dynamic: description
Dynamic: home-page
Dynamic: keywords
Dynamic: license
Dynamic: license-file
Dynamic: requires-dist
Dynamic: summary
